{
  "generatedAt": "2026-03-08T01:58:11.482Z",
  "issueNumber": 52,
  "scanTitle": "Alberta",
  "scannersInUse": [
    "axe",
    "alfa",
    "equalAccess",
    "accesslint",
    "qualweb"
  ],
  "scannerStats": {
    "axe": {
      "label": "axe",
      "failed": 81,
      "uniqueFailed": 81,
      "duplicates": 0
    },
    "alfa": {
      "label": "ALFA",
      "failed": 1458,
      "uniqueFailed": 1458,
      "duplicates": 0
    },
    "equalAccess": {
      "label": "Equal Access",
      "failed": 655,
      "uniqueFailed": 622,
      "duplicates": 33
    },
    "accesslint": {
      "label": "AccessLint",
      "failed": 99,
      "uniqueFailed": 99,
      "duplicates": 0
    },
    "qualweb": {
      "label": "QualWeb",
      "failed": 474,
      "uniqueFailed": 474,
      "duplicates": 0
    }
  },
  "matrix": {
    "axe": {
      "axe": 74,
      "alfa": 0,
      "equalAccess": 0,
      "accesslint": 0,
      "qualweb": 0
    },
    "alfa": {
      "axe": 0,
      "alfa": 367,
      "equalAccess": 0,
      "accesslint": 0,
      "qualweb": 0
    },
    "equalAccess": {
      "axe": 0,
      "alfa": 0,
      "equalAccess": 565,
      "accesslint": 0,
      "qualweb": 0
    },
    "accesslint": {
      "axe": 0,
      "alfa": 0,
      "equalAccess": 0,
      "accesslint": 94,
      "qualweb": 0
    },
    "qualweb": {
      "axe": 0,
      "alfa": 0,
      "equalAccess": 0,
      "accesslint": 0,
      "qualweb": 28
    }
  },
  "duplicateFindingTotals": 1536,
  "overlapEntryCount": 0,
  "overlapEntries": []
}
